odoo/addons/mrp_bom_simple_report/README.rst
odoo/addons/mrp_bom_simple_report/__init__.py
odoo/addons/mrp_bom_simple_report/__manifest__.py
odoo/addons/mrp_bom_simple_report/i18n/fr.po
odoo/addons/mrp_bom_simple_report/i18n/it.po
odoo/addons/mrp_bom_simple_report/i18n/mrp_bom_simple_report.pot
odoo/addons/mrp_bom_simple_report/readme/CONTRIBUTORS.rst
odoo/addons/mrp_bom_simple_report/readme/DESCRIPTION.rst
odoo/addons/mrp_bom_simple_report/report/ir_actions_report.xml
odoo/addons/mrp_bom_simple_report/report/report_simple_bom.xml
odoo/addons/mrp_bom_simple_report/static/description/bom_simple_report_new_action.jpeg
odoo/addons/mrp_bom_simple_report/static/description/bom_simple_report_new_report.png
odoo/addons/mrp_bom_simple_report/static/description/icon.png
odoo/addons/mrp_bom_simple_report/static/description/index.html
odoo/addons/mrp_bom_simple_report/static/src/scss/mrp_bom_simple_report.scss
odoo_addon_mrp_bom_simple_report-16.0.1.0.0.3.dist-info/METADATA
odoo_addon_mrp_bom_simple_report-16.0.1.0.0.3.dist-info/WHEEL
odoo_addon_mrp_bom_simple_report-16.0.1.0.0.3.dist-info/top_level.txt
odoo_addon_mrp_bom_simple_report-16.0.1.0.0.3.dist-info/RECORD
